pyred/RedDBStream.py
pyred/__init__.py
pyred/core/Column.py
pyred/core/Table.py
pyred/core/__init__.py
pyred/core/tools/__init__.py
pyred/core/tools/compare.py
pyred/core/tools/print_colors.py
pyred-0.3.46.dist-info/LICENSE
pyred-0.3.46.dist-info/METADATA
pyred-0.3.46.dist-info/WHEEL
pyred-0.3.46.dist-info/top_level.txt
pyred-0.3.46.dist-info/RECORD
