Metadata-Version: 2.1
Name: pyred
Version: 0.3.46
Summary: Easily send data to Amazon Redshift
Home-page: https://github.com/dacker-team/pyred
Author: Dacker
Author-email: hello@dacker.co
License: UNKNOWN
Keywords: send data amazon redshift easy
Platform: UNKNOWN
Classifier: Programming Language :: Python :: 3
Classifier: License :: OSI Approved :: MIT License
Classifier: Operating System :: OS Independent
Requires-Python: >=3
Requires-Dist: psycopg2-binary (>=2.7.4)
Requires-Dist: pandas (>=0.25.0)
Requires-Dist: dbstream (>=0.0.23)
